Metadata-Version: 1.1
Name: PrtSc
Version: 1.0
Summary: It takes a screenshot
Home-page: UNKNOWN
Author: Pranav
Author-email: pranavcr7com@gmail.com
License: MIT
Platform: UNKNOWN
Classifier: License :: OSI Approved :: MIT License
Classifier: Programming Language :: Python :: 3.9
